skinnygrad/__init__.py
skinnygrad/autograd.py
skinnygrad/callbacks.py
skinnygrad/config.py
skinnygrad/layers.py
skinnygrad/llops.py
skinnygrad/optimizers.py
skinnygrad/runtime.py
skinnygrad/shapes.py
skinnygrad/tensors.py
skinnygrad-0.1.3.dist-info/LICENSE
skinnygrad-0.1.3.dist-info/METADATA
skinnygrad-0.1.3.dist-info/WHEEL
skinnygrad-0.1.3.dist-info/RECORD
