Metadata-Version: 2.1
Name: skinnygrad
Version: 0.1.3
Summary: autodiff engine inspired by tinygrad
License: MIT
Keywords: autodiff,automatic differentiation,machine learning,deep learning,tensor
Author: Arthur
Author-email: atte.book@gmail.com
Requires-Python: >=3.11,<4.0
Classifier: License :: OSI Approved :: MIT License
Classifier: Programming Language :: Python :: 3
Classifier: Programming Language :: Python :: 3.11
Classifier: Programming Language :: Python :: 3.12
Provides-Extra: gpu
Provides-Extra: logger
Provides-Extra: visualizer
Requires-Dist: numpy (>=2.0.0,<3.0.0)
Project-URL: homepage, https://github.com/ArthurBook/skinnygrad
Project-URL: repository, https://github.com/ArthurBook/skinnygrad
